[
    {
      "Name": "Pottery"
    },
    {
      "Name": "Furniture"
    },
    {
      "Name": "Crochet"
    },
    {
      "Name": "Leather"
    },
    {
      "Name": "Mat"
    },
    {
      "Name": "Embroidered dresses"
    },
    {
      "Name": "Ceramic"
    },
    {
      "Name": "clothes"
    },
    {
      "Name": "Cotton"
    },
    {
      "Name": "Marble and granite"
    },
    {
      "Name": "oils"
    },
    {
      "Name": "Dairy"
    },
    {
      "Name": "Meshabk"
    },
    {
      "Name": "Therapeutic sand"
    },
    {
      "Name": "Foods and oils"
    },
    {
      "Name": "dates"
    },
    {
      "Name": "Carpets"
    },
    {
      "Name": "Foods"
    },
    {
      "Name": "wood"
    },
    {
      "Name": "Cosmetics"
    },
    {
      "Name": "Copper products"
    }
  ]
  